cemit_calculator/__init__.py
cemit_calculator-0.0.4.dist-info/LICENCE.txt
cemit_calculator-0.0.4.dist-info/METADATA
cemit_calculator-0.0.4.dist-info/WHEEL
cemit_calculator-0.0.4.dist-info/top_level.txt
cemit_calculator-0.0.4.dist-info/RECORD
