Metadata-Version: 2.1
Name: cemit-calculator
Version: 0.0.4
Summary: A very basic calculator for cemit data scientist
Home-page: UNKNOWN
Author: Saiful Rayhan
Author-email: sirayhancse@gmail.com
License: MIT
Keywords: calculator
Platform: UNKNOWN
Classifier: Development Status :: 5 - Production/Stable
Classifier: Intended Audience :: Education
Classifier: License :: OSI Approved :: MIT License
Classifier: Programming Language :: Python :: 3
License-File: LICENCE.txt
